{
  "enumerationValueList": [
    {
      "ID": 75,
      "Name": "Mortar",
      "FriendlyName": "Mortar",
      "IsBallistic": true,
      "IsMissile": false,
      "IsEnergy": false,
      "IsSupport": false,
      "UsesInternalAmmo": false,
      "UIColorRef": "Ballistic",
      "FallbackUIColor": null,
      "Icon": "BallisticHardpointIcon",
      "OutOfAmmoAudioVOEvent": "AmmoDepleted_Multiple"
    },
    {
      "ID": 76,
      "Name": "LRIFLE",
      "FriendlyName": "Light Rifle",
      "IsBallistic": true,
      "IsMissile": false,
      "IsEnergy": false,
      "IsSupport": false,
      "UsesInternalAmmo": false,
      "UIColorRef": "Ballistic",
      "FallbackUIColor": null,
      "Icon": "BallisticHardpointIcon",
      "OutOfAmmoAudioVOEvent": "AmmoDepleted_AC5"
    },
    {
      "ID": 77,
      "Name": "MRIFLE",
      "FriendlyName": "Medium Rifle",
      "IsBallistic": true,
      "IsMissile": false,
      "IsEnergy": false,
      "IsSupport": false,
      "UsesInternalAmmo": false,
      "UIColorRef": "Ballistic",
      "FallbackUIColor": null,
      "Icon": "BallisticHardpointIcon",
      "OutOfAmmoAudioVOEvent": "AmmoDepleted_AC10"
    },
    {
      "ID": 78,
      "Name": "HRIFLE",
      "FriendlyName": "Heavy Rifle",
      "IsBallistic": true,
      "IsMissile": false,
      "IsEnergy": false,
      "IsSupport": false,
      "UsesInternalAmmo": false,
      "UIColorRef": "Ballistic",
      "FallbackUIColor": null,
      "Icon": "BallisticHardpointIcon",
      "OutOfAmmoAudioVOEvent": "AmmoDepleted_AC20"
    },
    {
      "ID": 79,
      "Name": "AC2RF",
      "FriendlyName": "Rapid-Fire AC/2",
      "IsBallistic": true,
      "IsMissile": false,
      "IsEnergy": false,
      "IsSupport": false,
      "UsesInternalAmmo": false,
      "UIColorRef": "Ballistic",
      "FallbackUIColor": null,
      "Icon": "BallisticHardpointIcon",
      "OutOfAmmoAudioVOEvent": "AmmoDepleted_AC2"
    },
    {
      "ID": 80,
      "Name": "AC5RF",
      "FriendlyName": "Rapid-Fire AC/5",
      "IsBallistic": true,
      "IsMissile": false,
      "IsEnergy": false,
      "IsSupport": false,
      "UsesInternalAmmo": false,
      "UIColorRef": "Ballistic",
      "FallbackUIColor": null,
      "Icon": "BallisticHardpointIcon",
      "OutOfAmmoAudioVOEvent": "AmmoDepleted_AC5"
    },
    {
      "ID": 81,
      "Name": "AC10RF",
      "FriendlyName": "Rapid-Fire AC/10",
      "IsBallistic": true,
      "IsMissile": false,
      "IsEnergy": false,
      "IsSupport": false,
      "UsesInternalAmmo": false,
      "UIColorRef": "Ballistic",
      "FallbackUIColor": null,
      "Icon": "BallisticHardpointIcon",
      "OutOfAmmoAudioVOEvent": "AmmoDepleted_AC10"
    },
    {
      "ID": 82,
      "Name": "AC20RF",
      "FriendlyName": "Rapid-Fire AC/20",
      "IsBallistic": true,
      "IsMissile": false,
      "IsEnergy": false,
      "IsSupport": false,
      "UsesInternalAmmo": false,
      "UIColorRef": "Ballistic",
      "FallbackUIColor": null,
      "Icon": "BallisticHardpointIcon",
      "OutOfAmmoAudioVOEvent": "AmmoDepleted_AC20"
    },
    {
      "ID": 83,
      "Name": "HVAC2",
      "FriendlyName": "HVAC/2",
      "IsBallistic": true,
      "IsMissile": false,
      "IsEnergy": false,
      "IsSupport": false,
      "UsesInternalAmmo": false,
      "UIColorRef": "Ballistic",
      "FallbackUIColor": null,
      "Icon": "BallisticHardpointIcon",
      "OutOfAmmoAudioVOEvent": "AmmoDepleted_AC2"
    },
    {
      "ID": 84,
      "Name": "HVAC5",
      "FriendlyName": "HVAC/5",
      "IsBallistic": true,
      "IsMissile": false,
      "IsEnergy": false,
      "IsSupport": false,
      "UsesInternalAmmo": false,
      "UIColorRef": "Ballistic",
      "FallbackUIColor": null,
      "Icon": "BallisticHardpointIcon",
      "OutOfAmmoAudioVOEvent": "AmmoDepleted_AC5"
    },
    {
      "ID": 85,
      "Name": "HVAC10",
      "FriendlyName": "HVAC/10",
      "IsBallistic": true,
      "IsMissile": false,
      "IsEnergy": false,
      "IsSupport": false,
      "UsesInternalAmmo": false,
      "UIColorRef": "Ballistic",
      "FallbackUIColor": null,
      "Icon": "BallisticHardpointIcon",
      "OutOfAmmoAudioVOEvent": "AmmoDepleted_AC10"
    },
    {
      "ID": 86,
      "Name": "HAG",
      "FriendlyName": "Hyper-Assault Gauss",
      "IsBallistic": true,
      "IsMissile": false,
      "IsEnergy": false,
      "IsSupport": false,
      "UsesInternalAmmo": false,
      "UIColorRef": "Ballistic",
      "FallbackUIColor": null,
      "Icon": "BallisticHardpointIcon",
      "OutOfAmmoAudioVOEvent": "AmmoDepleted_Gauss"
    },
    {
      "ID": 87,
      "Name": "CM50",
      "FriendlyName": "Cruise Missile/50",
      "IsBallistic": false,
      "IsMissile": true,
      "IsEnergy": false,
      "IsSupport": false,
      "UsesInternalAmmo": false,
      "UIColorRef": "Missile",
      "FallbackUIColor": null,
      "Icon": "MissileHardpointIcon",
      "OutOfAmmoAudioVOEvent": "AmmoDepleted_LRM"
    },
    {
      "ID": 88,
      "Name": "Fluid",
      "FriendlyName": "Fluid",
      "IsBallistic": false,
      "IsMissile": false,
      "IsEnergy": false,
      "IsSupport": true,
      "UsesInternalAmmo": false,
      "UIColorRef": "Small",
      "FallbackUIColor": null,
      "Icon": "SmallHardpointIcon",
      "OutOfAmmoAudioVOEvent": "AmmoDepleted_Flamer"
    }
  ]
}