{
  "VehicleTags": {
    "items": [
      "mr-resize-1.5",
      "unit_vehicle",
      "unit_vehicle_carrier",
      "unit_heavy",
      "unit_tracks",
      "unit_lance_support",
      "unit_range_medium",
      "unit_armor_low",
      "unit_speed_low",
      "NoBiome_lunarVacuum",
      "NoBiome_martianVacuum",
      "unit_release"
    ],
    "tagSetSourceFile": ""
  },
  "ChassisID": "vehiclechassisdef_CARRIER_SRM",
  "Description": {
    "Id": "vehicledef_CARRIER_SRM",
    "Name": "SRM Carrier",
    "UIName": "SRM Carrier (Standard)",
    "Details": "<b>Name: <color=#85DBF6>SRM Carrier</color>\nArmor: <color=#85DBF6>Standard </color>\tTechnology: <color=#85DBF6>Inner Sphere</color>\nMovement: <color=#85DBF6>3/5 (Tracked)</color>\tEngine: <color=#85DBF6>180 ICE</color></b>\n\nFor centuries, mobile missile systems have been a staple of military forces. Missile Carriers play a crucial role in battles across the Inner Sphere, offering a potent mix of firepower and mobility.\n\nThis modern version mounts ten forward-firing SRM-6 launchers. While the SRM carrier must physically move to change firing angles, a barrage fired from a missile carrier is a fearsome sight, and four tons of ammunition allow a carrier to keep up that rate of fire for over a minute, but force carriers to be tied to a functioning supply system to keep them in action for any extended period.",
    "Icon": "uixVhclIcon_srmcarrier",
    "Cost": 1933000,
    "Rarity": 0,
    "Purchasable": true
  },
  "Version": 1,
  "Locations": [
    {
      "Location": "Front",
      "CurrentArmor": 60,
      "CurrentInternalStructure": 30,
      "AssignedArmor": 60,
      "DamageLevel": "Functional"
    },
    {
      "Location": "Left",
      "CurrentArmor": 60,
      "CurrentInternalStructure": 30,
      "AssignedArmor": 60,
      "DamageLevel": "Functional"
    },
    {
      "Location": "Right",
      "CurrentArmor": 60,
      "CurrentInternalStructure": 30,
      "AssignedArmor": 60,
      "DamageLevel": "Functional"
    },
    {
      "Location": "Rear",
      "CurrentArmor": 60,
      "CurrentInternalStructure": 30,
      "AssignedArmor": 60,
      "DamageLevel": "Functional"
    }
  ],
  "inventory": [
    {
      "ComponentDefID": "Weapon_SRM_SRM6_0-STOCK",
      "ComponentDefType": "Weapon",
      "MountedLocation": "Front",
      "HardpointSlot": 0,
      "DamageLevel": "Functional"
    },
    {
      "ComponentDefID": "Weapon_SRM_SRM6_0-STOCK",
      "ComponentDefType": "Weapon",
      "MountedLocation": "Front",
      "HardpointSlot": 1,
      "DamageLevel": "Functional"
    },
    {
      "ComponentDefID": "Weapon_SRM_SRM6_0-STOCK",
      "ComponentDefType": "Weapon",
      "MountedLocation": "Front",
      "HardpointSlot": 2,
      "DamageLevel": "Functional"
    },
    {
      "ComponentDefID": "Weapon_SRM_SRM6_0-STOCK",
      "ComponentDefType": "Weapon",
      "MountedLocation": "Front",
      "HardpointSlot": 3,
      "DamageLevel": "Functional"
    },
    {
      "ComponentDefID": "Weapon_SRM_SRM6_0-STOCK",
      "ComponentDefType": "Weapon",
      "MountedLocation": "Front",
      "HardpointSlot": 4,
      "DamageLevel": "Functional"
    },
    {
      "ComponentDefID": "Weapon_SRM_SRM6_0-STOCK",
      "ComponentDefType": "Weapon",
      "MountedLocation": "Front",
      "HardpointSlot": 5,
      "DamageLevel": "Functional"
    },
    {
      "ComponentDefID": "Weapon_SRM_SRM6_0-STOCK",
      "ComponentDefType": "Weapon",
      "MountedLocation": "Front",
      "HardpointSlot": 6,
      "DamageLevel": "Functional"
    },
    {
      "ComponentDefID": "Weapon_SRM_SRM6_0-STOCK",
      "ComponentDefType": "Weapon",
      "MountedLocation": "Front",
      "HardpointSlot": 7,
      "DamageLevel": "Functional"
    },
    {
      "ComponentDefID": "Weapon_SRM_SRM6_0-STOCK",
      "ComponentDefType": "Weapon",
      "MountedLocation": "Front",
      "HardpointSlot": 8,
      "DamageLevel": "Functional"
    },
    {
      "ComponentDefID": "Weapon_SRM_SRM6_0-STOCK",
      "ComponentDefType": "Weapon",
      "MountedLocation": "Front",
      "HardpointSlot": 9,
      "DamageLevel": "Functional"
    },
    {
      "ComponentDefID": "Ammo_AmmunitionBox_Generic_SRM",
      "ComponentDefType": "AmmunitionBox",
      "MountedLocation": "Front",
      "HardpointSlot": -1,
      "DamageLevel": "Functional"
    },
    {
      "ComponentDefID": "Ammo_AmmunitionBox_Generic_SRM",
      "ComponentDefType": "AmmunitionBox",
      "MountedLocation": "Front",
      "HardpointSlot": -1,
      "DamageLevel": "Functional"
    },
    {
      "ComponentDefID": "Ammo_AmmunitionBox_Generic_SRM",
      "ComponentDefType": "AmmunitionBox",
      "MountedLocation": "Front",
      "HardpointSlot": -1,
      "DamageLevel": "Functional"
    },
    {
      "ComponentDefID": "Ammo_AmmunitionBox_Generic_SRM",
      "ComponentDefType": "AmmunitionBox",
      "MountedLocation": "Front",
      "HardpointSlot": -1,
      "DamageLevel": "Functional"
    }
  ],
  "MinAppearanceDate": "2470-01-01T00:00:00Z"
}