{
  "VehicleTags": {
    "items": [
      "mr-resize-1.1",
      "unit_vehicle",
      "unit_light",
      "unit_wheels",
      "unit_lance_vanguard",
      "unit_range_long",
      "unit_armor_medium",
      "unit_speed_high",
      "unit_release",
      "unit_veepack"
    ],
    "tagSetSourceFile": ""
  },
  "ChassisID": "vehiclechassisdef_CHEVALIER_SPEED",
  "Description": {
    "Id": "vehicledef_CHEVALIER_SPEED",
    "Name": "Chevalier Light Tank",
    "UIName": "Chevalier Light Tank (Speed)",
    "Details": "<b>Name: <color=#85DBF6>Chevalier Light Tank (Speed)</color>\nArmor: <color=#85DBF6>Standard </color>\tTechnology: <color=#85DBF6>Inner Sphere</color>\nMovement: <color=#85DBF6>8/13 (Wheeled)</color>\tEngine: <color=#85DBF6>225 Fusion</color></b>",
    "Icon": "uixVhclIcon_chevalier",
    "Cost": 1058088,
    "Rarity": 0,
    "Purchasable": true
  },
  "Version": 1,
  "Locations": [
    {
      "Location": "Front",
      "CurrentArmor": 90,
      "CurrentInternalStructure": 20,
      "AssignedArmor": 90,
      "DamageLevel": "Functional"
    },
    {
      "Location": "Left",
      "CurrentArmor": 70,
      "CurrentInternalStructure": 20,
      "AssignedArmor": 70,
      "DamageLevel": "Functional"
    },
    {
      "Location": "Right",
      "CurrentArmor": 70,
      "CurrentInternalStructure": 20,
      "AssignedArmor": 70,
      "DamageLevel": "Functional"
    },
    {
      "Location": "Rear",
      "CurrentArmor": 50,
      "CurrentInternalStructure": 20,
      "AssignedArmor": 50,
      "DamageLevel": "Functional"
    },
    {
      "Location": "Turret",
      "CurrentArmor": 80,
      "CurrentInternalStructure": 20,
      "AssignedArmor": 80,
      "DamageLevel": "Functional"
    }
  ],
  "inventory": [
    {
      "ComponentDefID": "Weapon_SRM_SSRM2_0-STOCK",
      "ComponentDefType": "Weapon",
      "MountedLocation": "Front",
      "HardpointSlot": 0,
      "DamageLevel": "Functional"
    },
    {
      "ComponentDefID": "Weapon_Laser_LargeLaserER_NU_0-STOCK",
      "ComponentDefType": "Weapon",
      "MountedLocation": "Turret",
      "HardpointSlot": 0,
      "DamageLevel": "Functional"
    },
    {
      "ComponentDefID": "Ammo_AmmunitionBox_Generic_SRM",
      "ComponentDefType": "AmmunitionBox",
      "MountedLocation": "Front",
      "HardpointSlot": -1,
      "DamageLevel": "Functional"
    }
  ],
  "MinAppearanceDate": "3051-01-01T00:00:00Z"
}