{
  "VehicleTags": {
    "items": [
      "mr-resize-1-1-0.85",
      "unit_vehicle",
      "unit_light",
      "unit_hover",
      "unit_lance_vanguard",
      "unit_lance_tank",
      "unit_range_long",
      "unit_armor_high",
      "unit_speed_high",
      "unit_release",
      "unit_veepack"
    ],
    "tagSetSourceFile": ""
  },
  "ChassisID": "vehiclechassisdef_JEdgar_Cell",
  "Description": {
    "Id": "vehicledef_JEdgar_Cell",
    "Name": "J. Edgar Light Hover Tank",
    "UIName": "J. Edgar Light Hover Tank (Cell)",
    "Details": "<b>Name: <color=#85DBF6>J. Edgar Light Hover Tank (Cell)</color>\nArmor: <color=#85DBF6>Standard</color>\tTechnology: <color=#85DBF6>Inner Sphere</color>\nMovement: <color=#85DBF6>12/20 (Hover)</color>\tEngine: <color=#85DBF6>145 Fuel Cell</color></b>",
    "Icon": "uixVhclIcon_jedgar",
    "Cost": 563875,
    "Rarity": 0,
    "Purchasable": true
  },
  "Version": 1,
  "Locations": [
    {
      "Location": "Front",
      "CurrentArmor": 150,
      "CurrentInternalStructure": 15,
      "AssignedArmor": 150,
      "DamageLevel": "Functional"
    },
    {
      "Location": "Left",
      "CurrentArmor": 95,
      "CurrentInternalStructure": 15,
      "AssignedArmor": 95,
      "DamageLevel": "Functional"
    },
    {
      "Location": "Right",
      "CurrentArmor": 95,
      "CurrentInternalStructure": 15,
      "AssignedArmor": 95,
      "DamageLevel": "Functional"
    },
    {
      "Location": "Rear",
      "CurrentArmor": 60,
      "CurrentInternalStructure": 15,
      "AssignedArmor": 60,
      "DamageLevel": "Functional"
    },
    {
      "Location": "Turret",
      "CurrentArmor": 120,
      "CurrentInternalStructure": 15,
      "AssignedArmor": 120,
      "DamageLevel": "Functional"
    }
  ],
  "inventory": [
    {
      "ComponentDefID": "Weapon_Rifle_LightRifle_0-STOCK",
      "ComponentDefType": "Weapon",
      "MountedLocation": "Turret",
      "HardpointSlot": 0,
      "DamageLevel": "Functional"
    },
    {
      "ComponentDefID": "Weapon_MachineGun_MachineGun_0-STOCK",
      "ComponentDefType": "Weapon",
      "MountedLocation": "Turret",
      "HardpointSlot": 1,
      "DamageLevel": "Functional"
    },
    {
      "ComponentDefID": "Weapon_MachineGun_MachineGun_0-STOCK",
      "ComponentDefType": "Weapon",
      "MountedLocation": "Turret",
      "HardpointSlot": 2,
      "DamageLevel": "Functional"
    },
    {
      "ComponentDefID": "Ammo_AmmunitionBox_Generic_Rifle_Light",
      "ComponentDefType": "AmmunitionBox",
      "MountedLocation": "Front",
      "HardpointSlot": -1,
      "DamageLevel": "Functional"
    },
    {
      "ComponentDefID": "Ammo_AmmunitionBox_Generic_MG_Half",
      "ComponentDefType": "AmmunitionBox",
      "MountedLocation": "Front",
      "HardpointSlot": -1,
      "DamageLevel": "Functional"
    },
    {
      "ComponentDefID": "Gear_Hover",
      "ComponentDefType": "Upgrade",
      "MountedLocation": "Front",
      "HardpointSlot": -1,
      "DamageLevel": "Functional"
    }
  ],
  "MinAppearanceDate": "2998-01-01T00:00:00Z"
}